nano_gpt/__init__.py
nano_gpt/checkpoint.py
nano_gpt/config.py
nano_gpt/devices.py
nano_gpt/hellaswag_eval.py
nano_gpt/log.py
nano_gpt/model.py
nano_gpt/tokenizer.py
nano_gpt/trainer.py
nano_gpt/datasets/__init__.py
nano_gpt/datasets/data_loader.py
nano_gpt/datasets/finewebedu.py
nano_gpt/datasets/hellaswag.py
nano_gpt/datasets/tinyshakespeare.py
nano_gpt/tool/__init__.py
nano_gpt/tool/__main__.py
nano_gpt/tool/eval.py
nano_gpt/tool/export.py
nano_gpt/tool/model_config.py
nano_gpt/tool/prepare_dataset.py
nano_gpt/tool/sample.py
nano_gpt/tool/train.py
nano_gpt-0.1.0.dist-info/licenses/LICENSE
nano_gpt-0.1.0.dist-info/METADATA
nano_gpt-0.1.0.dist-info/WHEEL
nano_gpt-0.1.0.dist-info/entry_points.txt
nano_gpt-0.1.0.dist-info/top_level.txt
nano_gpt-0.1.0.dist-info/RECORD
