Metadata-Version: 2.4
Name: nano_gpt
Version: 0.1.0
Summary: A GPT-2 reproduction following karpathy's nanoGPT youtube videos
Home-page: https://github.com/allenporter/nano_gpt
Author: Allen Porter
Author-email: allen.porter@gmail.com
License: MIT
Classifier: License :: OSI Approved :: Apache Software License
Classifier: License :: OSI Approved :: MIT License
Classifier: Programming Language :: Python :: 3
Classifier: Programming Language :: Python :: 3 :: Only
Requires-Python: >=3.10
License-File: LICENSE
Requires-Dist: datasets>=3.3.2
Requires-Dist: tiktoken>=0.9.0
Requires-Dist: transformers>=4.49.0
Requires-Dist: torch
Dynamic: license-file
